Metadata-Version: 2.1
Name: m0smithpy
Version: 0.1.0
Summary: Helper functions and missing functions from the Python core
Classifier: Programming Language :: Python :: 3
Classifier: License :: OSI Approved :: MIT License
Classifier: Operating System :: OS Independent
Requires-Python: >=3.6
